easy_vk/__init__.py
easy_vk/api_category/__init__.py
easy_vk/api_category/api_category.py
easy_vk/bot/__init__.py
easy_vk/bot/bot.py
easy_vk/bot/handlers.py
easy_vk/bot/keyboard.py
easy_vk/bot/lonpoll.py
easy_vk/bot/api/__init__.py
easy_vk/bot/api/appWidgets.py
easy_vk/bot/api/board.py
easy_vk/bot/api/docs.py
easy_vk/bot/api/groups.py
easy_vk/bot/api/messages.py
easy_vk/bot/api/photos.py
easy_vk/bot/api/storage.py
easy_vk/bot/api/stories.py
easy_vk/bot/api/users.py
easy_vk/bot/api/utils.py
easy_vk/bot/api/wall.py
easy_vk/bot/update_types/__init__.py
easy_vk/bot/update_types/update_types.py
easy_vk/exceptions/__init__.py
easy_vk/exceptions/exceptions.py
easy_vk/parser/__init__.py
easy_vk/parser/parser.py
easy_vk/types/__init__.py
easy_vk/types/objects.py
easy_vk/types/responses.py
easy_vk/user/__init__.py
easy_vk/user/user.py
easy_vk/user/api/__init__.py
easy_vk/user/api/account.py
easy_vk/user/api/ads.py
easy_vk/user/api/apps.py
easy_vk/user/api/auth.py
easy_vk/user/api/board.py
easy_vk/user/api/database.py
easy_vk/user/api/docs.py
easy_vk/user/api/downloadedGames.py
easy_vk/user/api/fave.py
easy_vk/user/api/friends.py
easy_vk/user/api/gifts.py
easy_vk/user/api/groups.py
easy_vk/user/api/leads.py
easy_vk/user/api/likes.py
easy_vk/user/api/market.py
easy_vk/user/api/messages.py
easy_vk/user/api/newsfeed.py
easy_vk/user/api/notes.py
easy_vk/user/api/notifications.py
easy_vk/user/api/orders.py
easy_vk/user/api/pages.py
easy_vk/user/api/photos.py
easy_vk/user/api/polls.py
easy_vk/user/api/prettyCards.py
easy_vk/user/api/search.py
easy_vk/user/api/stats.py
easy_vk/user/api/status.py
easy_vk/user/api/storage.py
easy_vk/user/api/stories.py
easy_vk/user/api/streaming.py
easy_vk/user/api/users.py
easy_vk/user/api/utils.py
easy_vk/user/api/video.py
easy_vk/user/api/wall.py
easy_vk/user/api/widgets.py
easy_vk-0.0.37.dist-info/LICENSE
easy_vk-0.0.37.dist-info/METADATA
easy_vk-0.0.37.dist-info/WHEEL
easy_vk-0.0.37.dist-info/top_level.txt
easy_vk-0.0.37.dist-info/RECORD
