Metadata-Version: 2.1
Name: easy-vk
Version: 0.0.37
Summary: Обертка для VK api
Home-page: https://github.com/Phinnik/easy_vk
Author: Phinnik
Author-email: elecdron@gmail.com
License: UNKNOWN
Platform: UNKNOWN
Classifier: Programming Language :: Python :: 3
Classifier: License :: OSI Approved :: MIT License
Classifier: Operating System :: OS Independent
Requires-Python: >=3.6, <3.8
Requires-Dist: requests
Requires-Dist: aiohttp
Requires-Dist: pydantic
